crl_api/__init__.py
crl_api/auth.py
crl_api/client.py
crl_api/exceptions.py
crl_api/models.py
crl_sdk/__init__.py
crl_sdk-1.0.0.dist-info/METADATA
crl_sdk-1.0.0.dist-info/WHEEL
crl_sdk-1.0.0.dist-info/top_level.txt
crl_sdk-1.0.0.dist-info/RECORD
