Metadata-Version: 2.1
Name: crl-sdk
Version: 1.0.0
Summary: CRL Technologies API Client
Home-page: https://crl-technologies.com
Author: CRL Technologies
Author-email: andrea@crl-technologies.com
Requires-Python: >=3.8
Requires-Dist: requests >=2.31.0
